uniform_signal_interp/__init__.py
uniform_signal_interp/uniform_signal_interp.cp312-win_amd64.pyd
uniform_signal_interp/uniform_signal_interp.pyi
uniform_signal_interp-0.2.dist-info/licenses/LICENSE
uniform_signal_interp-0.2.dist-info/METADATA
uniform_signal_interp-0.2.dist-info/WHEEL
uniform_signal_interp-0.2.dist-info/top_level.txt
uniform_signal_interp-0.2.dist-info/RECORD
