Metadata-Version: 2.4
Name: uniform_signal_interp
Version: 0.2
Summary: Interpolation of uniformly sampled signal.
Author-email: Shibo Xu <sbxu@zju.edu.cn>
Classifier: Programming Language :: Python :: 3
Classifier: Operating System :: Microsoft :: Windows
Requires-Python: >=3.9
License-File: LICENSE
Requires-Dist: numpy>=1.13.3
Dynamic: license-file
